benchmarks/__init__.py
benchmarks/base.py
benchmarks/rosenbrock.py
benchmarks/sphere.py
config/__init__.py
config/params.py
core/__init__.py
core/objective_interface.py
core/abc/__init__.py
core/abc/abc.py
core/abc/artificial_bee.py
core/abc/employee_bee.py
core/abc/food_source.py
core/abc/onlooker_bee.py
core/abc/scout_bee.py
core/nas/__init__.py
core/nas/act.py
core/nas/evaluation_strategy.py
core/nas/momentum_eval.py
core/nas/nas_interface.py
core/nas/search_space.py
utils/__init__.py
utils/file_handler.py
utils/image_aug.py
utils/logger.py
utils/prompt_handler.py
HiveNAS-0.1.5.dist-info/LICENSE
HiveNAS-0.1.5.dist-info/METADATA
HiveNAS-0.1.5.dist-info/WHEEL
HiveNAS-0.1.5.dist-info/top_level.txt
HiveNAS-0.1.5.dist-info/RECORD
