Metadata-Version: 2.1
Name: HiveNAS
Version: 0.1.5
Summary: A Neural Architecture Search framework based on Artificial Bee Colony optimization
Home-page: https://github.com/ThunderStruct/HiveNAS
Author: Mohamed Shahawy
Author-email: mohamedshahawy@icloud.com
Keywords: nas neural architecture search optimization automl
Classifier: Intended Audience :: Developers
Classifier: Intended Audience :: Science/Research
Classifier: Topic :: Education
Classifier: Topic :: Scientific/Engineering :: Artificial Intelligence
Classifier: Topic :: Utilities
Classifier: Framework :: Jupyter
Classifier: Framework :: IPython
Classifier: License :: OSI Approved :: MIT License
Classifier: Programming Language :: Python :: 3.7
Classifier: Programming Language :: Python :: 3.9
Classifier: Programming Language :: Python :: 3.10
Classifier: Operating System :: MacOS
Classifier: Operating System :: Microsoft :: Windows
Classifier: Operating System :: POSIX :: Linux
Requires-Python: >=3.7
License-File: LICENSE
